__init__.py
mipha/__init__.py
mipha/factory.py
mipha/framework.py
mipha-0.1.1.dist-info/LICENSE.txt
mipha-0.1.1.dist-info/METADATA
mipha-0.1.1.dist-info/WHEEL
mipha-0.1.1.dist-info/top_level.txt
mipha-0.1.1.dist-info/RECORD
