Metadata-Version: 2.1
Name: mipha
Version: 0.1.1
Summary: Modular data Integration for Predictive Healthcare Analytics
Author-email: Hadrien Salem <hadrien.salem@centralelille.fr>
Maintainer-email: Hadrien Salem <hadrien.salem@centralelille.fr>
License: MIT License
Project-URL: Homepage, https://github.com/SnowHawkeye/mipha
Project-URL: Bug Reports, https://github.com/SnowHawkeye/mipha/issues
Project-URL: Source, https://github.com/SnowHawkeye/mipha
Keywords: machine learning,data science,healthcare,disease prediction
Classifier: Development Status :: 3 - Alpha
Classifier: Intended Audience :: Developers
Classifier: Topic :: Software Development :: Build Tools
Classifier: License :: OSI Approved :: MIT License
Classifier: Programming Language :: Python :: 3.12
Requires-Python: >=3.12
License-File: LICENSE.txt
Provides-Extra: dev
Requires-Dist: check-manifest ; extra == 'dev'
Provides-Extra: test
Requires-Dist: coverage ; extra == 'test'
